{"id":"4B758FE6-D2B5-463D-8E25-502CB4D90376","model_name_ssi":"Document","model_pk_ssi":"f4bbb9dc-c74f-45c2-80e7-ddb38aabf45f","gbl_mdVersion_s":"Aardvark","dct_references_s":"{\"urn:x-esri:serviceType:ArcGIS#FeatureLayer\":\"https://services3.arcgis.com/n6uYoouQZW75n5WI/arcgis/rest/services/Wisconsin_Statewide_Parcels/FeatureServer/0\",\"http://schema.org/url\":\"https://www.sco.wisc.edu/parcels/data/\",\"http://schema.org/downloadUrl\":[{\"url\":\"https://web.s3.wisc.edu/parcels/v10_parcels/V10.0.0_Wisconsin_Parcels_2024_10.3_Compressed.zip\",\"label\":\"Geodatabase\"}],\"http://www.isotc211.org/schemas/2005/gmd/\":\"https://web.s3.wisc.edu/rml-gisdata/metadata/WI_Parcels_2024.xml\"}","dct_title_s":"Parcels Wisconsin (Statewide), 2024","dct_description_sm":["This is the final deliverable for the Version 10 Statewide Parcel Map Database Project (V10). This feature class represents a comprehensive, spatially referenced collection of parcel geometries as recognized by local-level governments within the State of Wisconsin (the feature class is aggregated from county level and municipal-level data). See the Project Homepage for more detail on the parameters for how data was prepared and submitted to this project: https://www.sco.wisc.edu/parcels/submission/. Schema documentation can be found within this feature class metadata and here: https://www.sco.wisc.edu/parcels/data/assets/V10/V10_Wisconsin_Statewide_Parcels_Schema_Documentation.pdf Change log and known issues can be found here: https://www.sco.wisc.edu/parcels/data/assets/Wisconsin_Statewide_Parcels_Change_Log.pdf."],"b1g_websitePlatform_s":"GeoBlacklight","b1g_dateAccessioned_dt":"2026-01-06T00:00:00Z","dct_format_s":"Geodatabase","geomg_id_s":"4B758FE6-D2B5-463D-8E25-502CB4D90376","b1g_publication_state_s":"published","b1g_dct_accrualMethod_s":"Mediated deposit","pcdm_memberOf_sm":["dc8c18df-7d64-4ff4-a754-d18d0891187d"],"dct_isPartOf_sm":["10d-03"],"b1g_access_s":"{}","b1g_language_sm":["English"],"dct_temporal_sm":["2024"],"gbl_indexYear_im":[2024],"gbl_dateRange_drsim":["[2024 TO 2024]"],"dct_spatial_sm":["Wisconsin"],"dcat_bbox":"ENVELOPE(-92.964,-86.666,47.083,42.457)","locn_geometry":"POLYGON((-92.964 47.083, -86.666 47.083, -86.666 42.457, -92.964 42.457, -92.964 47.083))","b1g_dcat_endpointURL_s":"https://github.com/opengeometadata/edu.wisc","dcat_centroid":"44.769999999999996,-89.815","b1g_dcat_endpointDescription_s":"GitHub","schema_provider_s":"UW-Madison Robinson Map Library","gbl_resourceClass_sm":["Datasets"],"gbl_resourceType_sm":["Polygon data"],"gbl_displayNote_sm":["Info: This is an archived dataset at UW-Madison."],"dct_creator_sm":["Wisconsin Department of Administration"],"dct_subject_sm":["Planning and Cadastral"],"dcat_theme_sm":["Property"],"dct_language_sm":["eng"],"date_created_dtsi":"2024-08-10T00:00:00Z","date_modified_dtsi":"2026-01-14T00:00:00Z","dct_accessRights_s":"Public","dct_identifier_sm":["https://geodata.wisc.edu/catalog/4B758FE6-D2B5-463D-8E25-502CB4D90376"],"b1g_code_s":"10","b1g_localCollectionLabel_sm":["Statewide","Wisconsin State Agencies"],"b1g_harvestWorkflow_s":"py_ogm_wisc","gbl_mdModified_dt":"2026-01-14T00:00:00Z","b1g_geom_import_id_ssi":"582","_version_":1854324988446769152,"timestamp":"2026-01-14T20:21:55.752Z","solr_bboxtype__minX":-92.964,"solr_bboxtype__minY":42.457,"solr_bboxtype__maxX":-86.666,"solr_bboxtype__maxY":47.083}