{"id":"999-0003-007","model_name_ssi":"Document","model_pk_ssi":"64ace82f-e9ff-4420-a29d-2b03153fbc1a","gbl_mdVersion_s":"Aardvark","dct_references_s":"{\"http://lccn.loc.gov/sh85035852\":\"https://www.policymap.com/maps\"}","dct_title_s":"Education (PolicyMap)","dct_description_sm":["Education is a category of data layers within the PolicyMap application. To find each layer, log in to PolicyMap, select a category, and browse to the desired layer."],"b1g_dateAccessioned_dt":"2021-03-15T00:00:00Z","dct_format_s":"Tabular Data","dct_relation_sm":["8888-001"],"geomg_id_s":"999-0003-007","b1g_publication_state_s":"published","b1g_dct_accrualMethod_s":"Manual curation","pcdm_memberOf_sm":["999-licensed-resources"],"dct_isPartOf_sm":["999-0003"],"b1g_access_s":"{\"03\":\"https://purl.lib.uiowa.edu/PolicyMap\",\"04\":\"https://www.lib.umd.edu/dbfinder/id/UMD09180\",\"05\":\"https://primo.lib.umn.edu/permalink/f/1q7ssba/UMN_ALMA61817563030001701\",\"06\":\"http://catalog.lib.msu.edu/record=b10238077~S39a\",\"07\":\"https://search.lib.umich.edu/databases/record/39117\",\"09\":\"https://libraries.psu.edu/databases/psu01762\",\"10\":\"https://digital.library.wisc.edu/1711.web/policymap\",\"11\":\"https://library.ohio-state.edu/record=e1001956~S7\",\"12\":\"http://pi.lib.uchicago.edu/1001/cat/bib/12539126\",\"14\":\"https://rutgers.primo.exlibrisgroup.com/discovery/fulldisplay?docid=alma991031283143504646\\u0026context=L\\u0026vid=01RUT_INST:01RUT\\u0026search_scope=MyInst_and_CI_2\\u0026tab=Everything_except_research\\u0026lang=en\"}","b1g_language_sm":["English"],"gbl_indexYear_im":[2020],"gbl_dateRange_drsim":["[2020 TO 2020]"],"dct_spatial_sm":["United States"],"dcat_bbox":"ENVELOPE(-179.9,-64.4,71.6,-14.8)","locn_geometry":"POLYGON((-179.9 71.6, -64.4 71.6, -64.4 -14.8, -179.9 -14.8, -179.9 71.6))","b1g_dct_mediator_sm":["University of Chicago","University of Iowa","University of Maryland","University of Michigan","Michigan State University","University of Minnesota","The Ohio State University","Pennsylvania State University","Rutgers University-New Brunswick","University of Wisconsin-Madison"],"dcat_centroid":"28.4,-122.15","schema_provider_s":"PolicyMap","gbl_resourceClass_sm":["Datasets"],"gbl_displayNote_sm":["Warning: Requires logging in through an organization with licensed access. Different institutions may have licenses for different years or locations."],"dcat_keyword_sm":["Policy Map","Policy"],"dct_language_sm":["eng"],"date_created_dtsi":"2021-04-27T00:00:00Z","date_modified_dtsi":"2026-01-14T00:00:00Z","dct_accessRights_s":"Restricted","dct_identifier_sm":["999-0003-007"],"b1g_code_s":"999-0003","gbl_mdModified_dt":"2026-01-14T00:00:00Z","b1g_geom_import_id_ssi":"581","_version_":1854317626366361600,"timestamp":"2026-01-14T18:24:54.725Z","solr_bboxtype__minX":-179.9,"solr_bboxtype__minY":-14.8,"solr_bboxtype__maxX":-64.4,"solr_bboxtype__maxY":71.6}